{"A":[{"nombre":"QUIMICA GENERAL","sis":"2004046","nivel":"A","grupos":[{"grupo":"1","titular":{"docente":"HOEPFNER REYNOLDS MAURICIO","horarios":[{"dia":"MI","hora":"6:45-8:15","aula":"623"},{"dia":"JU","hora":"14:15-15:45","aula":"612"},{"dia":"VI","hora":"17:15-18:45","aula":"622"}]},"auxiliar":{}},{"grupo":"2","titular":{"docente":"MUNOZ COLLAZOS MARIA SUSANA DEL","horarios":[{"dia":"LU","hora":"12:45-14:15","aula":"624"},{"dia":"MI","hora":"17:15-18:45","aula":"607"},{"dia":"VI","hora":"12:45-14:15","aula":"691D"}]},"auxiliar":{}},{"grupo":"7","titular":{"docente":"HERBAS ANGULO ADELINA","horarios":[{"dia":"MA","hora":"17:15-18:45","aula":"691C"},{"dia":"MI","hora":"12:45-14:15","aula":"622"},{"dia":"JU","hora":"15:45-17:15","aula":"692A"}]},"auxiliar":{}}]},{"nombre":"FISICA BASICA I","sis":"2006018","nivel":"A","grupos":[{"grupo":"H","titular":{"docente":"TORRICO TROCHE MILKA MONICA","horarios":[{"dia":"LU","hora":"11:15-12:45","aula":"692B"},{"dia":"MI","hora":"11:15-12:45","aula":"691D"},{"dia":"VI","hora":"11:15-12:45","aula":"624"}]},"auxiliar":{}},{"grupo":"H1","titular":{},"auxiliar":{"nombre":"PEREZ CESPEDES ROBERTO","horarios":[{"dia":"MA","hora":"12:45-14:15","aula":"618"}]}},{"grupo":"H2","titular":{},"auxiliar":{"nombre":"CASTRO LAZARTE CECILIA BEATRIZ","horarios":[{"dia":"MA","hora":"18:45-20:15","aula":"621"}]}},{"grupo":"H3","titular":{},"auxiliar":{"nombre":"LUCANO LUCANO MARCELO JAVIER","horarios":[{"dia":"MI","hora":"14:15-15:45","aula":"621"}]}},{"grupo":"H4","titular":{},"auxiliar":{"nombre":"DAVALOS BROZOVIC JORGE","horarios":[{"dia":"JU","hora":"8:15-9:45","aula":"621"}]}},{"grupo":"H5","titular":{},"auxiliar":{"nombre":"GUZMAN SAAVEDRA ROCIO","horarios":[{"dia":"LU","hora":"8:15-9:45","aula":"620"}]}},{"grupo":"I","titular":{"docente":"CHOQUE UNO FRANCISCO","horarios":[{"dia":"MA","hora":"8:15-9:45","aula":"642"},{"dia":"MI","hora":"9:45-11:15","aula":"691F"},{"dia":"JU","hora":"11:15-12:45","aula":"692F"}]},"auxiliar":{}},{"grupo":"I1","titular":{},"auxiliar":{"nombre":"VARGAS VALLEJOS LUZ VIRGINIA","horarios":[{"dia":"LU","hora":"17:15-18:45","aula":"618"}]}},{"grupo":"I2","titular":{},"auxiliar":{"nombre":"DAVALOS BROZOVIC JORGE","horarios":[{"dia":"MI","hora":"11:15-12:45","aula":"618"}]}},{"grupo":"I3","titular":{},"auxiliar":{"nombre":"TORREZ PELAEZ RAUL WILDER","horarios":[{"dia":"MI","hora":"17:15-18:45","aula":"621"}]}},{"grupo":"I4","titular":{},"auxiliar":{"nombre":"CLAROS CRUZ LUIS GUALBERTO","horarios":[{"dia":"VI","hora":"11:15-12:45","aula":"621"}]}},{"grupo":"I5","titular":{},"auxiliar":{"nombre":"VARGAS REINAGA JUAN CARLOS","horarios":[{"dia":"VI","hora":"8:15-9:45","aula":"618"}]}},{"grupo":"J","titular":{"docente":"FUENTES MIRANDA IVAN","horarios":[{"dia":"MI","hora":"18:45-20:15","aula":"692E"},{"dia":"VI","hora":"6:45-8:15","aula":"693C"},{"dia":"SA","hora":"11:15-12:45","aula":"693B"}]},"auxiliar":{}},{"grupo":"J1","titular":{},"auxiliar":{"nombre":"GUTIERREZ MARTINEZ VICTOR","horarios":[{"dia":"LU","hora":"6:45-8:15","aula":"618"}]}},{"grupo":"J2","titular":{},"auxiliar":{"nombre":"SHITIKOV GAGARINA GALINA","horarios":[{"dia":"MI","hora":"14:15-15:45","aula":"618"}]}},{"grupo":"J3","titular":{},"auxiliar":{"nombre":"ORDONEZ SALVATIERRA MIGUEL ANGEL","horarios":[{"dia":"LU","hora":"17:15-18:45","aula":"620"}]}},{"grupo":"J4","titular":{},"auxiliar":{"nombre":"CLAROS CRUZ LUIS GUALBERTO","horarios":[{"dia":"LU","hora":"14:15-15:45","aula":"618"}]}},{"grupo":"K","titular":{"docente":"RUIZ UCUMARI IVAN","horarios":[{"dia":"LU","hora":"8:15-9:45","aula":"693A"},{"dia":"MI","hora":"6:45-8:15","aula":"692E"},{"dia":"VI","hora":"6:45-8:15","aula":"692E"}]},"auxiliar":{}},{"grupo":"K1","titular":{},"auxiliar":{"nombre":"PEREZ CESPEDES ROBERTO","horarios":[{"dia":"LU","hora":"9:45-11:15","aula":"621"}]}},{"grupo":"K2","titular":{},"auxiliar":{"nombre":"GARCIA ANTURIANO OSCAR RICARDO","horarios":[{"dia":"MI","hora":"15:45-17:15","aula":"621"}]}},{"grupo":"K3","titular":{},"auxiliar":{"nombre":"ORDONEZ SALVATIERRA MIGUEL ANGEL","horarios":[{"dia":"JU","hora":"15:45-17:15","aula":"620"}]}},{"grupo":"K4","titular":{},"auxiliar":{"nombre":"CUELLAR OLIVERA OSCAR","horarios":[{"dia":"MI","hora":"6:45-8:15","aula":"618"}]}},{"grupo":"L","titular":{"docente":"CHOQUE UNO FRANCISCO","horarios":[{"dia":"MA","hora":"11:15-12:45","aula":"624"},{"dia":"JU","hora":"8:15-9:45","aula":"642"},{"dia":"VI","hora":"11:15-12:45","aula":"623"}]},"auxiliar":{}},{"grupo":"L1","titular":{},"auxiliar":{"nombre":"LUCANO LUCANO MARCELO JAVIER","horarios":[{"dia":"MA","hora":"14:15-15:45","aula":"621"}]}},{"grupo":"L2","titular":{},"auxiliar":{"nombre":"ALISS PAREDES EMILIO","horarios":[{"dia":"MI","hora":"6:45-8:15","aula":"621"}]}},{"grupo":"L3","titular":{},"auxiliar":{"nombre":"TORREZ PELAEZ RAUL WILDER","horarios":[{"dia":"JU","hora":"14:15-15:45","aula":"618"}]}}]},{"nombre":"ALGEBRA I","sis":"2008019","nivel":"A","grupos":[{"grupo":"3","titular":{"docente":"OMONTE OJALVO JOSE GIL","horarios":[{"dia":"MA","hora":"9:45-11:15","aula":"623"},{"dia":"JU","hora":"9:45-11:15","aula":"612"},{"dia":"SA","hora":"8:15-9:45","aula":"622"}]},"auxiliar":{}},{"grupo":"4","titular":{"docente":"PATINO TITO RONALD EDGAR","horarios":[{"dia":"LU","hora":"18:45-20:15","aula":"690E"},{"dia":"MI","hora":"17:15-18:45","aula":"661"}]},"auxiliar":{"nombre":"MENDEZ LOZA MARIEL ANGELES","horarios":[{"dia":"JU","hora":"9:45-11:15","aula":"622"}]}},{"grupo":"3A","titular":{"docente":"VARGAS PEREDO EMIR FELIX","horarios":[{"dia":"MA","hora":"11:15-12:45","aula":"692C"},{"dia":"VI","hora":"8:15-9:45","aula":"625D"}]},"auxiliar":{}},{"grupo":"4A","titular":{"docente":"LEON ROMERO GUALBERTO","horarios":[{"dia":"LU","hora":"12:45-14:15","aula":"692E"},{"dia":"MA","hora":"11:15-12:45","aula":"693D"},{"dia":"JU","hora":"6:45-8:15","aula":"692F"}]},"auxiliar":{}}]},{"nombre":"CALCULO I","sis":"2008054","nivel":"A","grupos":[{"grupo":"5","titular":{"docente":"FLORES GARCIA HERNAN","horarios":[{"dia":"JU","hora":"8:15-9:45","aula":"612"},{"dia":"VI","hora":"11:15-12:45","aula":"617B"}]},"auxiliar":{"nombre":"IBARRA VAQUILLA OSMAR","horarios":[{"dia":"SA","hora":"8:15-9:45","aula":"617C"}]}},{"grupo":"6","titular":{"docente":"OMONTE OJALVO JOSE GIL","horarios":[{"dia":"MA","hora":"11:15-12:45","aula":"692A"},{"dia":"MI","hora":"9:45-11:15","aula":"692D"},{"dia":"VI","hora":"8:15-9:45","aula":"691C"}]},"auxiliar":{}},{"grupo":"21","titular":{"docente":"GONZALES CARTAGENA LUCIO","horarios":[{"dia":"LU","hora":"8:15-9:45","aula":"691A"},{"dia":"MI","hora":"8:15-9:45","aula":"642"}]},"auxiliar":{"nombre":"FLORES VARGAS JORGE EDUARDO","horarios":[{"dia":"SA","hora":"9:45-11:15","aula":"651"}]}},{"grupo":"5A","titular":{"docente":"DELGADILLO COSSIO DAVID ALFREDO","horarios":[{"dia":"LU","hora":"12:45-14:15","aula":"691D"},{"dia":"MA","hora":"12:45-14:15","aula":"617"},{"dia":"MI","hora":"12:45-14:15","aula":"607"}]},"auxiliar":{}},{"grupo":"6A","titular":{"docente":"HERBAS MALDONADO EDGARDO","horarios":[{"dia":"MA","hora":"14:15-15:45","aula":"642"},{"dia":"VI","hora":"8:15-9:45","aula":"661"}]},"auxiliar":{}}]},{"nombre":"COMPUTACION I","sis":"2010008","nivel":"A","grupos":[{"grupo":"1","titular":{"docente":"USTARIZ VARGAS HERNAN","horarios":[{"dia":"LU","hora":"18:45-20:15","aula":"692B"},{"dia":"MI","hora":"18:45-20:15","aula":"692B"}]},"auxiliar":{"nombre":"TORREZ ARANCIBIA SERGIO","horarios":[{"dia":"SA","hora":"11:15-12:45","aula":"607"}]}},{"grupo":"2","titular":{"docente":"VARGAS COLQUE AIDEE","horarios":[{"dia":"MI","hora":"18:45-20:15","aula":"691C"},{"dia":"JU","hora":"18:45-20:15","aula":"691F"}]},"auxiliar":{"nombre":"ALVAREZ CORRALES HENRIQUE","horarios":[{"dia":"SA","hora":"11:15-12:45","aula":"691B"}]}},{"grupo":"4","titular":{"docente":"VARGAS COLQUE AIDEE","horarios":[{"dia":"LU","hora":"18:45-20:15","aula":"692A"},{"dia":"MA","hora":"18:45-20:15","aula":"692B"}]},"auxiliar":{"nombre":"AUXILIAR POR DESIGNAR","horarios":[{"dia":"MI","hora":"15:45-17:15","aula":"693B"}]}},{"grupo":"5","titular":{"docente":"USTARIZ VARGAS HERNAN","horarios":[{"dia":"MA","hora":"12:45-14:15","aula":"691F"},{"dia":"JU","hora":"12:45-14:15","aula":"692B"}]},"auxiliar":{"nombre":"AUXILIAR POR DESIGNAR","horarios":[{"dia":"SA","hora":"9:45-11:15","aula":"607"}]}}]}],"B":[{"nombre":"FISICA BASICA II","sis":"2006019","nivel":"B","grupos":[{"grupo":"F","titular":{"docente":"GARCIA ANTURIANO OSCAR RICARDO","horarios":[{"dia":"LU","hora":"11:15-12:45","aula":"623"},{"dia":"MA","hora":"11:15-12:45","aula":"691C"},{"dia":"VI","hora":"11:15-12:45","aula":"692B"}]},"auxiliar":{}},{"grupo":"F1","titular":{},"auxiliar":{"nombre":"GARCIA ANTURIANO OSCAR RICARDO","horarios":[{"dia":"LU","hora":"15:45-17:15","aula":"684L0"}]}},{"grupo":"F2","titular":{},"auxiliar":{"nombre":"CLAROS CRUZ LUIS GUALBERTO","horarios":[{"dia":"MI","hora":"12:45-14:15","aula":"684L0"}]}},{"grupo":"F3","titular":{},"auxiliar":{"nombre":"DAVALOS BROZOVIC JORGE","horarios":[{"dia":"JU","hora":"9:45-11:15","aula":"684L0"}]}},{"grupo":"F4","titular":{},"auxiliar":{"nombre":"VASQUEZ CARRILLO MICHAEL HUASCAR","horarios":[{"dia":"MI","hora":"14:15-15:45","aula":"684L0"}]}},{"grupo":"G","titular":{"docente":"TORRICO TROCHE MILKA MONICA","horarios":[{"dia":"MA","hora":"8:15-9:45","aula":"693D"},{"dia":"JU","hora":"11:15-12:45","aula":"692B"},{"dia":"VI","hora":"8:15-9:45","aula":"691B"}]},"auxiliar":{}},{"grupo":"G1","titular":{},"auxiliar":{"nombre":"UGARTE CEJAS FELIX","horarios":[{"dia":"LU","hora":"11:15-12:45","aula":"684L0"}]}},{"grupo":"G2","titular":{},"auxiliar":{"nombre":"FUENTES MIRANDA IVAN","horarios":[{"dia":"LU","hora":"18:45-20:15","aula":"684L8"}]}},{"grupo":"G3","titular":{},"auxiliar":{"nombre":"PEREZ CESPEDES ROBERTO","horarios":[{"dia":"JU","hora":"8:15-9:45","aula":"684L0"}]}},{"grupo":"H","titular":{"docente":"CASTRO LAZARTE CECILIA BEATRIZ","horarios":[{"dia":"LU","hora":"17:15-18:45","aula":"617"},{"dia":"MI","hora":"14:15-15:45","aula":"691B"},{"dia":"JU","hora":"15:45-17:15","aula":"691A"}]},"auxiliar":{}},{"grupo":"H1","titular":{},"auxiliar":{"nombre":"GUTIERREZ MARTINEZ VICTOR","horarios":[{"dia":"MI","hora":"8:15-9:45","aula":"684L0"}]}},{"grupo":"H2","titular":{},"auxiliar":{"nombre":"CASTRO LAZARTE CECILIA BEATRIZ","horarios":[{"dia":"MI","hora":"17:15-18:45","aula":"684L0"}]}},{"grupo":"H3","titular":{},"auxiliar":{"nombre":"DAVALOS BROZOVIC JORGE","horarios":[{"dia":"JU","hora":"11:15-12:45","aula":"684L0"}]}},{"grupo":"M","titular":{"docente":"CLAROS CRUZ LUIS GUALBERTO","horarios":[{"dia":"LU","hora":"15:45-17:15","aula":"624"},{"dia":"MA","hora":"15:45-17:15","aula":"623"},{"dia":"JU","hora":"12:45-14:15","aula":"691C"}]},"auxiliar":{}},{"grupo":"M1","titular":{},"auxiliar":{"nombre":"SHITIKOV GAGARINA GALINA","horarios":[{"dia":"MA","hora":"14:15-15:45","aula":"684L0"}]}},{"grupo":"M2","titular":{},"auxiliar":{"nombre":"DAVALOS BROZOVIC JORGE","horarios":[{"dia":"JU","hora":"18:45-20:15","aula":"684L0"}]}},{"grupo":"M3","titular":{},"auxiliar":{"nombre":"GUZMAN SAAVEDRA ROCIO","horarios":[{"dia":"LU","hora":"11:15-12:45","aula":"684L8"}]}},{"grupo":"M4","titular":{},"auxiliar":{"nombre":"VARGAS REINAGA JUAN CARLOS","horarios":[{"dia":"JU","hora":"15:45-17:15","aula":"684L0"}]}}]},{"nombre":"ALGEBRA II","sis":"2008022","nivel":"B","grupos":[{"grupo":"4","titular":{"docente":"MEDINA GAMBOA JULIO","horarios":[{"dia":"LU","hora":"6:45-8:15","aula":"692D"},{"dia":"MA","hora":"6:45-8:15","aula":"623"}]},"auxiliar":{"nombre":"QUISPE MEDRANO REINALDO","horarios":[{"dia":"VI","hora":"6:45-8:15","aula":"690D"}]}},{"grupo":"4A","titular":{"docente":"SALINAS PERICON WALTER OSCAR","horarios":[{"dia":"LU","hora":"15:45-17:15","aula":"693D"},{"dia":"MI","hora":"17:15-18:45","aula":"692F"},{"dia":"VI","hora":"14:15-15:45","aula":"623"}]},"auxiliar":{}}]},{"nombre":"CALCULO II","sis":"2008056","nivel":"B","grupos":[{"grupo":"4","titular":{"docente":"RELOS PACO SANTIAGO","horarios":[{"dia":"MA","hora":"18:45-20:15","aula":"692D"},{"dia":"SA","hora":"8:15-9:45","aula":"624"}]},"auxiliar":{"nombre":"FLORES VARGAS JORGE EDUARDO","horarios":[{"dia":"MI","hora":"15:45-17:15","aula":"607"}]}},{"grupo":"5","titular":{"docente":"FLORES GARCIA HERNAN","horarios":[{"dia":"LU","hora":"8:15-9:45","aula":"612"},{"dia":"MI","hora":"15:45-17:15","aula":"622"}]},"auxiliar":{"nombre":"ARANIBAR THONY INARA VALENTINA","horarios":[{"dia":"MA","hora":"6:45-8:15","aula":"617C"}]}},{"grupo":"13","titular":{"docente":"RELOS PACO SANTIAGO","horarios":[{"dia":"MA","hora":"15:45-17:15","aula":"693A"},{"dia":"VI","hora":"15:45-17:15","aula":"693C"}]},"auxiliar":{"nombre":"ARANIBAR THONY INARA VALENTINA","horarios":[{"dia":"JU","hora":"14:15-15:45","aula":"692F"}]}}]},{"nombre":"ESTADISTICA I","sis":"2008059","nivel":"B","grupos":[{"grupo":"1","titular":{"docente":"MANCHEGO CASTELLON ROBERTO JUAN","horarios":[{"dia":"MI","hora":"18:45-20:15","aula":"607"},{"dia":"VI","hora":"18:45-20:15","aula":"624"}]},"auxiliar":{"nombre":"ROMERO COCA MIROSLAVA LINNETE","horarios":[{"dia":"LU","hora":"14:15-15:45","aula":"692H"}]}},{"grupo":"2","titular":{"docente":"MANCHEGO CASTELLON ROBERTO JUAN","horarios":[{"dia":"MA","hora":"14:15-15:45","aula":"691F"},{"dia":"SA","hora":"11:15-12:45","aula":"623"}]},"auxiliar":{"nombre":"ROMERO COCA MIROSLAVA LINNETE","horarios":[{"dia":"MI","hora":"11:15-12:45","aula":"692G"}]}}]},{"nombre":"DIBUJO TECNICO COMPUTARIZADO","sis":"2018007","nivel":"B","grupos":[{"grupo":"1","titular":{"docente":"MENDEZ VELASQUEZ IVAN","horarios":[{"dia":"LU","hora":"17:15-18:45","aula":"692E"},{"dia":"JU","hora":"17:15-19:30","aula":"623"}]},"auxiliar":{}},{"grupo":"2","titular":{"docente":"MENDEZ VELASQUEZ IVAN","horarios":[{"dia":"MA","hora":"17:15-18:45","aula":"691A"},{"dia":"VI","hora":"16:30-18:45","aula":"692F"}]},"auxiliar":{}}]}],"C":[{"nombre":"FISICOQUIMICA","sis":"2004044","nivel":"C","grupos":[{"grupo":"1","titular":{"docente":"GONZALES CARTAGENA LUCIO","horarios":[{"dia":"JU","hora":"6:45-8:15","aula":"623"},{"dia":"SA","hora":"8:15-9:45","aula":"691F"}]},"auxiliar":{"nombre":"ROMERO COCA DAYANA NICOLE","horarios":[{"dia":"JU","hora":"15:45-17:15","aula":"691B"}]}}]},{"nombre":"FISICA BASICA III","sis":"2006020","nivel":"C","grupos":[{"grupo":"C1","titular":{},"auxiliar":{"nombre":"AGREDA CORRALES LUIS ROBERTO","horarios":[{"dia":"MI","hora":"14:15-15:45","aula":"684L8"}]}},{"grupo":"C3","titular":{},"auxiliar":{"nombre":"VASQUEZ CARRILLO MICHAEL HUASCAR","horarios":[{"dia":"MA","hora":"11:15-12:45","aula":"684L8"}]}},{"grupo":"D2","titular":{},"auxiliar":{"nombre":"AGREDA CORRALES LUIS ROBERTO","horarios":[{"dia":"MA","hora":"14:15-15:45","aula":"684L8"}]}},{"grupo":"D4","titular":{},"auxiliar":{"nombre":"GUZMAN SAAVEDRA ROCIO","horarios":[{"dia":"VI","hora":"8:15-9:45","aula":"684L8"}]}},{"grupo":"E","titular":{"docente":"RUIZ UCUMARI IVAN","horarios":[{"dia":"MA","hora":"6:45-8:15","aula":"692E"},{"dia":"MI","hora":"8:15-9:45","aula":"617"},{"dia":"VI","hora":"8:15-9:45","aula":"693B"}]},"auxiliar":{}},{"grupo":"E1","titular":{},"auxiliar":{"nombre":"AGREDA CORRALES LUIS ROBERTO","horarios":[{"dia":"LU","hora":"9:45-11:15","aula":"684L8"}]}},{"grupo":"E2","titular":{},"auxiliar":{"nombre":"GUZMAN SAAVEDRA ROCIO","horarios":[{"dia":"MA","hora":"8:15-9:45","aula":"684L8"}]}},{"grupo":"E3","titular":{},"auxiliar":{"nombre":"AGREDA CORRALES LUIS ROBERTO","horarios":[{"dia":"MI","hora":"11:15-12:45","aula":"684L8"}]}},{"grupo":"E4","titular":{},"auxiliar":{"nombre":"CASTRO LAZARTE CECILIA BEATRIZ","horarios":[{"dia":"MI","hora":"18:45-20:15","aula":"684L8"}]}},{"grupo":"F","titular":{"docente":"CHOQUE UNO FRANCISCO","horarios":[{"dia":"MA","hora":"9:45-11:15","aula":"617"},{"dia":"MI","hora":"8:15-9:45","aula":"692A"},{"dia":"VI","hora":"8:15-9:45","aula":"692E"}]},"auxiliar":{}},{"grupo":"F1","titular":{},"auxiliar":{"nombre":"AGREDA CORRALES LUIS ROBERTO","horarios":[{"dia":"LU","hora":"8:15-9:45","aula":"684L8"}]}},{"grupo":"F2","titular":{},"auxiliar":{"nombre":"AGREDA CORRALES LUIS ROBERTO","horarios":[{"dia":"MI","hora":"9:45-11:15","aula":"684L8"}]}},{"grupo":"F3","titular":{},"auxiliar":{"nombre":"ORDONEZ SALVATIERRA MIGUEL ANGEL","horarios":[{"dia":"JU","hora":"17:15-18:45","aula":"684L8"}]}}]},{"nombre":"CALCULO COMPUTARIZADO","sis":"2008043","nivel":"C","grupos":[{"grupo":"1","titular":{"docente":"JUCHANI BAZUALDO DEMETRIO","horarios":[{"dia":"MA","hora":"12:45-14:15","aula":"691E"},{"dia":"JU","hora":"9:45-11:15","aula":"642"},{"dia":"VI","hora":"11:15-12:45","aula":"692E"}]},"auxiliar":{}},{"grupo":"2","titular":{"docente":"JUCHANI BAZUALDO DEMETRIO","horarios":[{"dia":"MA","hora":"14:15-15:45","aula":"612"},{"dia":"MI","hora":"14:15-15:45","aula":"692B"},{"dia":"VI","hora":"12:45-14:15","aula":"691E"}]},"auxiliar":{}}]},{"nombre":"ECUACIONES DIFERENCIALES","sis":"2008058","nivel":"C","grupos":[{"grupo":"2","titular":{"docente":"MULLER SANTA CRUZ HANS CRISTIAN","horarios":[{"dia":"LU","hora":"17:15-18:45","aula":"607"},{"dia":"MI","hora":"17:15-18:45","aula":"624"}]},"auxiliar":{"nombre":"CHUCA CONDO LUIS ALBERTO","horarios":[{"dia":"MA","hora":"11:15-12:45","aula":"692G"}]}},{"grupo":"2A","titular":{"docente":"MULLER SANTA CRUZ HANS CRISTIAN","horarios":[{"dia":"MA","hora":"8:15-9:45","aula":"623"},{"dia":"JU","hora":"8:15-9:45","aula":"624"}]},"auxiliar":{"nombre":"CHUCA CONDO LUIS ALBERTO","horarios":[{"dia":"VI","hora":"9:45-11:15","aula":"624"}]}}]},{"nombre":"ESTADISTICA II","sis":"2008061","nivel":"C","grupos":[{"grupo":"1","titular":{"docente":"MANCHEGO CASTELLON ROBERTO JUAN","horarios":[{"dia":"MA","hora":"17:15-18:45","aula":"692D"},{"dia":"JU","hora":"14:15-15:45","aula":"622"},{"dia":"SA","hora":"9:45-11:15","aula":"612"}]},"auxiliar":{}},{"grupo":"4","titular":{"docente":"MANCHEGO CASTELLON ROBERTO JUAN","horarios":[{"dia":"LU","hora":"14:15-15:45","aula":"692E"},{"dia":"MI","hora":"15:45-17:15","aula":"624"},{"dia":"VI","hora":"17:15-18:45","aula":"612"}]},"auxiliar":{}}]}],"D":[{"nombre":"ELECTROTECNIA INDUSTRIAL","sis":"2014087","nivel":"D","grupos":[{"grupo":"1","titular":{"docente":"ORELLANA JIMENEZ JAIME","horarios":[{"dia":"LU","hora":"17:15-18:45","aula":"692H"},{"dia":"MI","hora":"18:45-20:15","aula":"642"},{"dia":"JU","hora":"15:45-17:15","aula":"617B"}]},"auxiliar":{"nombre":"ACHA PEREZ SAMUEL","horarios":[{"dia":"VI","hora":"17:15-19:30","aula":"682L3"}]}},{"grupo":"5","titular":{"docente":"ACHA PEREZ SAMUEL","horarios":[{"dia":"LU","hora":"6:45-8:15","aula":"692E"},{"dia":"MI","hora":"6:45-8:15","aula":"693B"}]},"auxiliar":{"nombre":"ACHA PEREZ SAMUEL","horarios":[{"dia":"MA","hora":"6:45-9:00","aula":"682L3"},{"dia":"SA","hora":"8:15-9:45","aula":"623"}]}}]},{"nombre":"ORGANIZACION INDUSTRIAL","sis":"2016010","nivel":"D","grupos":[{"grupo":"1","titular":{"docente":"RODRIGUEZ RAMIREZ CARLOS ALBERTO","horarios":[{"dia":"MA","hora":"6:45-8:15","aula":"693C"},{"dia":"JU","hora":"9:45-11:15","aula":"692D"},{"dia":"VI","hora":"6:45-8:15","aula":"691F"}]},"auxiliar":{}}]},{"nombre":"ECONOMIA INDUSTRIAL","sis":"2016011","nivel":"D","grupos":[{"grupo":"1","titular":{"docente":"GUTIERREZ ANDRADE OSVALDO WALTER","horarios":[{"dia":"LU","hora":"6:45-8:15","aula":"691D"},{"dia":"MI","hora":"6:45-8:15","aula":"692C"},{"dia":"SA","hora":"11:15-12:45","aula":"691C"}]},"auxiliar":{}},{"grupo":"2","titular":{"docente":"TRIGO ROCHA INGRID VICKY","horarios":[{"dia":"LU","hora":"14:15-15:45","aula":"690D"},{"dia":"MA","hora":"8:15-9:45","aula":"690D"},{"dia":"MI","hora":"8:15-9:45","aula":"690D"}]},"auxiliar":{}}]},{"nombre":"RESISTENCIA DE MATERIALES","sis":"2018006","nivel":"D","grupos":[{"grupo":"1","titular":{"docente":"GOMEZ UGARTE GUIDO","horarios":[{"dia":"MA","hora":"14:15-15:45","aula":"622"},{"dia":"MI","hora":"9:45-11:15","aula":"624"},{"dia":"MI","hora":"17:15-18:45","aula":"692E"}]},"auxiliar":{}}]},{"nombre":"TERMODINAMICA","sis":"2018009","nivel":"D","grupos":[{"grupo":"1","titular":{"docente":"TORREJON ROCABADO JULIO MARCELO","horarios":[{"dia":"LU","hora":"9:45-11:15","aula":"691C"},{"dia":"MI","hora":"14:15-15:45","aula":"693B"},{"dia":"JU","hora":"6:45-8:15","aula":"691D"}]},"auxiliar":{}}]}],"E":[{"nombre":"OPERACIONES INDUSTRIALES I","sis":"2016015","nivel":"E","grupos":[{"grupo":"1","titular":{"docente":"RIOJA CARDENAS GASTON GIL","horarios":[{"dia":"LU","hora":"9:45-11:15","aula":"692C"},{"dia":"MA","hora":"15:45-17:15","aula":"693B"},{"dia":"VI","hora":"8:15-9:45","aula":"692A"}]},"auxiliar":{}}]},{"nombre":"CONTABILIDAD BASICA","sis":"2016046","nivel":"E","grupos":[{"grupo":"1","titular":{"docente":"PEREZ FUENTES OMAR DAVID","horarios":[{"dia":"LU","hora":"14:15-15:45","aula":"623"},{"dia":"MA","hora":"14:15-15:45","aula":"693D"},{"dia":"MI","hora":"17:15-18:45","aula":"693D"}]},"auxiliar":{}},{"grupo":"3","titular":{"docente":"ARANIBAR LA FUENTE LIGIA","horarios":[{"dia":"LU","hora":"11:15-12:45","aula":"691F"},{"dia":"MI","hora":"9:45-11:15","aula":"660"},{"dia":"VI","hora":"11:15-12:45","aula":"692C"}]},"auxiliar":{}}]},{"nombre":"INVESTIGACION OPERATIVA I","sis":"2016048","nivel":"E","grupos":[{"grupo":"1","titular":{"docente":"PERICON BALDERRAMA ALFREDO","horarios":[{"dia":"LU","hora":"11:15-12:45","aula":"682L8IN"},{"dia":"MA","hora":"6:45-8:15","aula":"682L8IN"},{"dia":"MI","hora":"8:15-9:45","aula":"682L7IN"}]},"auxiliar":{}},{"grupo":"2","titular":{"docente":"QUIROZ CHAVEZ ABDON","horarios":[{"dia":"MA","hora":"9:45-11:15","aula":"652"},{"dia":"MI","hora":"14:15-15:45","aula":"692A"},{"dia":"JU","hora":"8:15-9:45","aula":"661"}]},"auxiliar":{}},{"grupo":"3","titular":{"docente":"QUIROZ CHAVEZ ABDON","horarios":[{"dia":"MA","hora":"11:15-12:45","aula":"692B"},{"dia":"MI","hora":"9:45-11:15","aula":"682L8IN"},{"dia":"JU","hora":"12:45-14:15","aula":"682L8IN"}]},"auxiliar":{}},{"grupo":"4","titular":{"docente":"REVOLLO TERAN LUZ MAYA","horarios":[{"dia":"LU","hora":"11:15-12:45","aula":"693C"},{"dia":"MA","hora":"11:15-12:45","aula":"693C"},{"dia":"JU","hora":"9:45-11:15","aula":"625D"}]},"auxiliar":{}},{"grupo":"5","titular":{"docente":"QUIROZ CHAVEZ ABDON","horarios":[{"dia":"MA","hora":"12:45-14:15","aula":"692A"},{"dia":"MI","hora":"8:15-9:45","aula":"625D"},{"dia":"JU","hora":"11:15-12:45","aula":"625C"}]},"auxiliar":{}}]},{"nombre":"MERCADOTECNIA","sis":"2016057","nivel":"E","grupos":[{"grupo":"1","titular":{"docente":"GUTIERREZ ANDRADE OSVALDO WALTER","horarios":[{"dia":"LU","hora":"18:45-20:15","aula":"693C"},{"dia":"SA","hora":"9:45-11:15","aula":"642"}]},"auxiliar":{}},{"grupo":"3","titular":{"docente":"SARMIENTO FRANCO ARIEL ANTONIO","horarios":[{"dia":"MA","hora":"18:45-20:15","aula":"623"},{"dia":"MI","hora":"18:45-20:15","aula":"690D"}]},"auxiliar":{}}]},{"nombre":"CIENCIA DE LOS MATERIALES","sis":"2018010","nivel":"E","grupos":[{"grupo":"1","titular":{"docente":"TORREJON ROCABADO JULIO MARCELO","horarios":[{"dia":"MA","hora":"15:45-17:15","aula":"691D"},{"dia":"MI","hora":"15:45-17:15","aula":"693C"}]},"auxiliar":{}}]},{"nombre":"ELEM. DE MAQUINAS Y TECNOL. MECANICA I","sis":"2018066","nivel":"E","grupos":[{"grupo":"1","titular":{"docente":"FERNANDEZ ROCHA LIDO","horarios":[{"dia":"MI","hora":"6:45-8:15","aula":"617B"},{"dia":"JU","hora":"6:45-8:15","aula":"CADCAM"},{"dia":"JU","hora":"17:15-18:45","aula":"692H"},{"dia":"VI","hora":"17:15-18:45","aula":"692A"}]},"auxiliar":{}},{"grupo":"2","titular":{"docente":"CRESPO GARCIA ALBERTO RUDY","horarios":[{"dia":"MI","hora":"20:15-21:45","aula":"625D"},{"dia":"JU","hora":"12:45-14:15","aula":"692D"}]},"auxiliar":{"nombre":"CRESPO GARCIA ALBERTO RUDY","horarios":[{"dia":"LU","hora":"14:15-17:15","aula":"682L8IN"}]}}]}],"F":[{"nombre":"OPERACIONES INDUSTRIALES II","sis":"2016019","nivel":"F","grupos":[{"grupo":"1","titular":{"docente":"ALFARO DENUS GONZALO","horarios":[{"dia":"JU","hora":"6:45-8:15","aula":"693A"},{"dia":"VI","hora":"6:45-8:15","aula":"693A"},{"dia":"SA","hora":"6:45-8:15","aula":"692E"}]},"auxiliar":{}}]},{"nombre":"INVESTIGACION DE MERCADOS","sis":"2016020","nivel":"F","grupos":[{"grupo":"1","titular":{"docente":"ALVAREZ QUIROZ RICHARD MILTON","horarios":[{"dia":"MA","hora":"18:45-21:00","aula":"692A"},{"dia":"JU","hora":"18:45-20:15","aula":"692D"}]},"auxiliar":{}},{"grupo":"2","titular":{"docente":"ALVAREZ QUIROZ RICHARD MILTON","horarios":[{"dia":"MA","hora":"17:15-18:45","aula":"682L8IN"},{"dia":"MI","hora":"11:15-13:30","aula":"682L8IN"}]},"auxiliar":{}}]},{"nombre":"COSTOS INDUSTRIALES","sis":"2016049","nivel":"F","grupos":[{"grupo":"1","titular":{"docente":"PEREZ FUENTES OMAR DAVID","horarios":[{"dia":"LU","hora":"15:45-17:15","aula":"691F"},{"dia":"MA","hora":"15:45-17:15","aula":"693C"},{"dia":"MI","hora":"12:45-14:15","aula":"691C"}]},"auxiliar":{}},{"grupo":"2","titular":{"docente":"LIMA VACAFLOR TITO ANIBAL","horarios":[{"dia":"LU","hora":"18:45-20:15","aula":"617"},{"dia":"MI","hora":"20:15-21:45","aula":"612"},{"dia":"SA","hora":"11:15-12:45","aula":"617"}]},"auxiliar":{}}]},{"nombre":"INVESTIGACION OPERATIVA II","sis":"2016051","nivel":"F","grupos":[{"grupo":"1","titular":{"docente":"MANCHEGO CASTELLON ROBERTO JUAN","horarios":[{"dia":"MA","hora":"15:45-17:15","aula":"692F"},{"dia":"JU","hora":"15:45-17:15","aula":"612"},{"dia":"VI","hora":"15:45-17:15","aula":"607"}]},"auxiliar":{}}]},{"nombre":"INGENIERIA DE METODOS Y REINGENIERIA","sis":"2016052","nivel":"F","grupos":[{"grupo":"1","titular":{"docente":"COSIO PAPADOPOLIS CARLOS JAVIER","horarios":[{"dia":"LU","hora":"17:15-18:45","aula":"682B"},{"dia":"MI","hora":"17:15-18:45","aula":"690C"},{"dia":"JU","hora":"6:45-8:15","aula":"692C"}]},"auxiliar":{"nombre":"AUXILIAR POR DESIGNAR","horarios":[{"dia":"MI","hora":"11:15-12:45","aula":"625D"}]}},{"grupo":"2","titular":{"docente":"COSIO PAPADOPOLIS CARLOS JAVIER","horarios":[{"dia":"MA","hora":"6:45-8:15","aula":"691B"},{"dia":"MI","hora":"8:15-9:45","aula":"691C"},{"dia":"VI","hora":"6:45-8:15","aula":"692A"}]},"auxiliar":{"nombre":"AUXILIAR POR DESIGNAR","horarios":[{"dia":"JU","hora":"8:15-9:45","aula":"617C"}]}},{"grupo":"3","titular":{"docente":"COSIO PAPADOPOLIS CARLOS JAVIER","horarios":[{"dia":"LU","hora":"8:15-9:45","aula":"682B"},{"dia":"MI","hora":"6:45-8:15","aula":"692A"},{"dia":"VI","hora":"8:15-9:45","aula":"682B"}]},"auxiliar":{}}]},{"nombre":"TECNOLOGIA MECANICA II","sis":"2018013","nivel":"F","grupos":[{"grupo":"1","titular":{"docente":"MARCA COLQUE RENE","horarios":[{"dia":"LU","hora":"20:15-21:45","aula":"691B"},{"dia":"JU","hora":"18:45-20:15","aula":"624"},{"dia":"VI","hora":"18:45-20:15","aula":"607"},{"dia":"SA","hora":"6:45-8:15","aula":"622"}]},"auxiliar":{}},{"grupo":"2","titular":{"docente":"MAMANI ALVAREZ JAVIER","horarios":[{"dia":"LU","hora":"17:15-18:45","aula":"651"},{"dia":"MA","hora":"20:15-21:45","aula":"691B"},{"dia":"JU","hora":"17:15-18:45","aula":"691B"},{"dia":"VI","hora":"17:15-18:45","aula":"642"}]},"auxiliar":{}}]}],"G":[{"nombre":"PLANIF. Y CONTROL DE LA PRODUCCION I","sis":"2016021","nivel":"G","grupos":[{"grupo":"1","titular":{"docente":"DOMINGUEZ GONZALES JACINTO GER","horarios":[{"dia":"LU","hora":"17:15-18:45","aula":"691A"},{"dia":"JU","hora":"11:15-12:45","aula":"682L8IN"},{"dia":"VI","hora":"11:15-12:45","aula":"682L6IN"}]},"auxiliar":{}},{"grupo":"2","titular":{"docente":"PEREZ FUENTES OMAR DAVID","horarios":[{"dia":"LU","hora":"12:45-14:15","aula":"692D"},{"dia":"MA","hora":"17:15-18:45","aula":"693A"},{"dia":"MI","hora":"15:45-17:15","aula":"693D"}]},"auxiliar":{}},{"grupo":"3","titular":{"docente":"QUIROZ CHAVEZ ABDON","horarios":[{"dia":"MA","hora":"8:15-9:45","aula":"661"},{"dia":"MI","hora":"11:15-12:45","aula":"691F"},{"dia":"JU","hora":"9:45-11:15","aula":"651"}]},"auxiliar":{}}]},{"nombre":"GESTION DE CALIDAD","sis":"2016022","nivel":"G","grupos":[{"grupo":"1","titular":{"docente":"COSIO PAPADOPOLIS CARLOS JAVIER","horarios":[{"dia":"MA","hora":"17:15-18:45","aula":"691F"},{"dia":"JU","hora":"17:15-18:45","aula":"682L0IN"},{"dia":"VI","hora":"17:15-18:45","aula":"692D"}]},"auxiliar":{}},{"grupo":"3","titular":{"docente":"COSIO PAPADOPOLIS CARLOS JAVIER","horarios":[{"dia":"LU","hora":"6:45-8:15","aula":"693C"},{"dia":"MA","hora":"8:15-9:45","aula":"682L0IN"},{"dia":"JU","hora":"8:15-9:45","aula":"682B"}]},"auxiliar":{}}]},{"nombre":"INGENIERIA ECONOMICA","sis":"2016023","nivel":"G","grupos":[{"grupo":"1","titular":{"docente":"Por Designar ...","horarios":[{"dia":"LU","hora":"20:15-21:45","aula":"622"},{"dia":"MA","hora":"20:15-21:45","aula":"607"},{"dia":"MI","hora":"18:45-20:15","aula":"692C"}]},"auxiliar":{}},{"grupo":"2","titular":{"docente":"Por Designar ...","horarios":[{"dia":"MA","hora":"8:15-9:45","aula":"AUDIND"},{"dia":"JU","hora":"8:15-9:45","aula":"684B"},{"dia":"VI","hora":"8:15-9:45","aula":"692B"}]},"auxiliar":{}},{"grupo":"3","titular":{"docente":"ARANIBAR LA FUENTE LIGIA","horarios":[{"dia":"LU","hora":"9:45-11:15","aula":"690C"},{"dia":"MI","hora":"12:45-14:15","aula":"692C"},{"dia":"VI","hora":"9:45-11:15","aula":"690B"}]},"auxiliar":{}},{"grupo":"4","titular":{"docente":"Por Designar ...","horarios":[{"dia":"LU","hora":"9:45-11:15","aula":"682L0IN"},{"dia":"MA","hora":"14:15-15:45","aula":"690B"},{"dia":"MI","hora":"6:45-8:15","aula":"690B"}]},"auxiliar":{}}]},{"nombre":"INGENIERIA DE SEGURIDAD","sis":"2016024","nivel":"G","grupos":[{"grupo":"1","titular":{"docente":"ARNEZ CAMACHO MARIA DEL CARMEN","horarios":[{"dia":"LU","hora":"8:15-9:45","aula":"692D"},{"dia":"MA","hora":"8:15-9:45","aula":"692D"},{"dia":"JU","hora":"8:15-9:45","aula":"692D"}]},"auxiliar":{"nombre":"AUXILIAR POR DESIGNAR","horarios":[{"dia":"JU","hora":"9:45-11:15","aula":"682L8IN"}]}},{"grupo":"2","titular":{"docente":"ARNEZ CAMACHO MARIA DEL CARMEN","horarios":[{"dia":"LU","hora":"9:45-11:15","aula":"682L6IN"},{"dia":"MA","hora":"9:45-11:15","aula":"682L8IN"},{"dia":"JU","hora":"9:45-11:15","aula":"682L6IN"}]},"auxiliar":{}}]},{"nombre":"OPERACIONES INDUSTRIALES III","sis":"2016025","nivel":"G","grupos":[{"grupo":"1","titular":{"docente":"GONZALES CARTAGENA LUCIO","horarios":[{"dia":"LU","hora":"18:45-20:15","aula":"691E"},{"dia":"MA","hora":"6:45-8:15","aula":"617"},{"dia":"SA","hora":"6:45-8:15","aula":"624"}]},"auxiliar":{}}]},{"nombre":"DISE¥O ASISTIDO POR COMPUTADORA","sis":"2016026","nivel":"G","grupos":[{"grupo":"1","titular":{"docente":"MALDONADO LOPEZ PASCUAL","horarios":[{"dia":"MA","hora":"18:45-20:15","aula":"691A"},{"dia":"VI","hora":"18:45-21:00","aula":"692E"}]},"auxiliar":{}}]}],"H":[{"nombre":"CONTROL Y AUTOMATIZACION INDUSTRIAL","sis":"2014088","nivel":"H","grupos":[{"grupo":"1","titular":{"docente":"COSSIO CABRERA WALTER FELIX","horarios":[{"dia":"MA","hora":"20:15-21:45","aula":"692F"},{"dia":"MI","hora":"20:15-21:45","aula":"692B"},{"dia":"JU","hora":"20:15-21:45","aula":"692B"}]},"auxiliar":{"nombre":"MARCA COLQUE FABIAN","horarios":[{"dia":"LU","hora":"6:45-8:15","aula":"682A"}]}}]},{"nombre":"PLANIF. Y CONTROL DE LA PRODUCCION II","sis":"2016027","nivel":"H","grupos":[{"grupo":"1","titular":{"docente":"DOMINGUEZ GONZALES JACINTO GER","horarios":[{"dia":"MA","hora":"17:15-18:45","aula":"682L6IN"},{"dia":"MI","hora":"11:15-12:45","aula":"682L6IN"},{"dia":"JU","hora":"17:15-18:45","aula":"692F"}]},"auxiliar":{}},{"grupo":"2","titular":{"docente":"PEREZ FUENTES OMAR DAVID","horarios":[{"dia":"LU","hora":"17:15-18:45","aula":"690C"},{"dia":"MA","hora":"12:45-14:15","aula":"692G"},{"dia":"MI","hora":"14:15-15:45","aula":"690D"}]},"auxiliar":{}},{"grupo":"3","titular":{"docente":"CHOQUE FLORES ALEX D'ANCHGELO","horarios":[{"dia":"MA","hora":"18:45-20:15","aula":"690B"},{"dia":"JU","hora":"18:45-20:15","aula":"625D"},{"dia":"SA","hora":"9:45-11:15","aula":"691F"}]},"auxiliar":{}}]},{"nombre":"INGENIERIA DE SISTEMAS I","sis":"2016028","nivel":"H","grupos":[{"grupo":"1","titular":{"docente":"CAMACHO VILLAZON JIMMY ERICK","horarios":[{"dia":"LU","hora":"18:45-20:15","aula":"642"},{"dia":"MI","hora":"18:45-20:15","aula":"661"},{"dia":"SA","hora":"11:15-12:45","aula":"612"}]},"auxiliar":{}}]},{"nombre":"PREP. Y EVAL. DE PROYECTOS I","sis":"2016029","nivel":"H","grupos":[{"grupo":"1","titular":{"docente":"Por Designar ...","horarios":[{"dia":"LU","hora":"20:15-21:45","aula":"693D"},{"dia":"MI","hora":"6:45-8:15","aula":"682L8IN"},{"dia":"JU","hora":"6:45-8:15","aula":"682L8IN"}]},"auxiliar":{}}]},{"nombre":"RECURSOS HUMANOS - PRODUCTIVIDAD","sis":"2016030","nivel":"H","grupos":[{"grupo":"1","titular":{"docente":"RODRIGUEZ RAMIREZ CARLOS ALBERTO","horarios":[{"dia":"LU","hora":"9:45-12:00","aula":"617"}]},"auxiliar":{}},{"grupo":"2","titular":{"docente":"VARGAS REINAGA JUAN CARLOS","horarios":[{"dia":"MA","hora":"18:45-21:00","aula":"682L8IN"}]},"auxiliar":{}}]},{"nombre":"PROCESOS INDUSTRIALES I","sis":"2016031","nivel":"H","grupos":[{"grupo":"1","titular":{"docente":"ECHEVERRIA HERRERA RODRIGO CARLOS","horarios":[{"dia":"LU","hora":"14:15-15:45","aula":"AULVIR"},{"dia":"MA","hora":"14:15-15:45","aula":"AULVIR"},{"dia":"MI","hora":"14:15-15:45","aula":"AUDIND"}]},"auxiliar":{}},{"grupo":"2","titular":{"docente":"VARGAS PEREDO EMIR FELIX","horarios":[{"dia":"MA","hora":"8:15-9:45","aula":"682L8IN"},{"dia":"MI","hora":"9:45-11:15","aula":"651"},{"dia":"VI","hora":"14:15-15:45","aula":"624"}]},"auxiliar":{}}]},{"nombre":"MANTENIMIENTO INDUSTRIAL","sis":"2018054","nivel":"H","grupos":[{"grupo":"1","titular":{"docente":"GOITIA ARZE OSCAR JAVIER","horarios":[{"dia":"VI","hora":"18:45-21:00","aula":"692D"},{"dia":"SA","hora":"8:15-9:45","aula":"691C"}]},"auxiliar":{}}]}],"I":[{"nombre":"INDUSTRIAS LACTEAS","sis":"2004206","nivel":"I","grupos":[{"grupo":"1","titular":{"docente":"GALARZA BARRON ANGEL","horarios":[{"dia":"MI","hora":"8:15-9:45","aula":"A808"},{"dia":"MI","hora":"9:45-12:00","aula":"L813"},{"dia":"JU","hora":"8:15-10:30","aula":"L813"}]},"auxiliar":{}}]},{"nombre":"INGENIERIA DE SISTEMAS II","sis":"2016032","nivel":"I","grupos":[{"grupo":"1","titular":{"docente":"CAMACHO VILLAZON JIMMY ERICK","horarios":[{"dia":"LU","hora":"20:15-21:45","aula":"612"},{"dia":"MI","hora":"20:15-21:45","aula":"692D"},{"dia":"SA","hora":"9:45-11:15","aula":"682L6IN"}]},"auxiliar":{}}]},{"nombre":"PREP. Y EVAL. DE PROYECTOS II","sis":"2016033","nivel":"I","grupos":[{"grupo":"1","titular":{"docente":"RODRIGUEZ OSTRIA JUAN CARLOS","horarios":[{"dia":"LU","hora":"18:45-20:15","aula":"682L6IN"},{"dia":"MA","hora":"6:45-8:15","aula":"693D"},{"dia":"MI","hora":"18:45-20:15","aula":"682L8IN"}]},"auxiliar":{}},{"grupo":"2","titular":{"docente":"CACERES CRUZ FRANZ ORLANDO","horarios":[{"dia":"MA","hora":"18:45-20:15","aula":"682L6IN"},{"dia":"MI","hora":"18:45-20:15","aula":"692G"},{"dia":"VI","hora":"18:45-20:15","aula":"691D"}]},"auxiliar":{}}]},{"nombre":"TALLER DE TESIS I","sis":"2016034","nivel":"I","grupos":[{"grupo":"1","titular":{"docente":"PEREZ FUENTES OMAR DAVID","horarios":[{"dia":"LU","hora":"18:45-20:15","aula":"693B"},{"dia":"LU","hora":"20:15-21:45","aula":"692F"},{"dia":"MA","hora":"18:45-20:15","aula":"660"}]},"auxiliar":{}},{"grupo":"2","titular":{"docente":"ARNEZ CAMACHO MARIA DEL CARMEN","horarios":[{"dia":"MA","hora":"11:15-14:15","aula":"682L6IN"},{"dia":"JU","hora":"6:45-8:15","aula":"682L0IN"}]},"auxiliar":{}}]},{"nombre":"PROCESOS INDUSTRIALES II","sis":"2016036","nivel":"I","grupos":[{"grupo":"1","titular":{"docente":"VARGAS PEREDO EMIR FELIX","horarios":[{"dia":"MA","hora":"9:45-11:15","aula":"690D"},{"dia":"MI","hora":"11:15-12:45","aula":"692E"},{"dia":"VI","hora":"15:45-17:15","aula":"624"}]},"auxiliar":{}}]},{"nombre":"GESTION Y CALIDAD AMBIENTAL","sis":"2018061","nivel":"I","grupos":[{"grupo":"1","titular":{"docente":"CRESPO GARCIA ALBERTO RUDY","horarios":[{"dia":"LU","hora":"20:15-21:45","aula":"682L8IN"},{"dia":"MA","hora":"12:45-14:15","aula":"682L8IN"},{"dia":"JU","hora":"19:30-21:45","aula":"682L8IN"}]},"auxiliar":{}}]}],"J":[{"nombre":"DERECHO EMPRESARIAL","sis":"2016038","nivel":"J","grupos":[{"grupo":"1","titular":{"docente":"JALDIN SALAZAR JUAN","horarios":[{"dia":"MA","hora":"19:30-21:45","aula":"691D"}]},"auxiliar":{}},{"grupo":"2","titular":{"docente":"JALDIN SALAZAR JUAN","horarios":[{"dia":"MI","hora":"19:30-21:45","aula":"693A"}]},"auxiliar":{}}]},{"nombre":"TALLER TESIS II","sis":"2016039","nivel":"J","grupos":[{"grupo":"1","titular":{"docente":"RODRIGUEZ RAMIREZ CARLOS ALBERTO","horarios":[{"dia":"MA","hora":"11:15-12:45","aula":"AUDIND"},{"dia":"MI","hora":"11:15-12:45","aula":"AUDIND"},{"dia":"JU","hora":"11:15-12:45","aula":"AUDIND"}]},"auxiliar":{}},{"grupo":"2","titular":{"docente":"ARNEZ CAMACHO MARIA DEL CARMEN","horarios":[{"dia":"LU","hora":"6:45-8:15","aula":"682L0IN"},{"dia":"JU","hora":"11:15-14:15","aula":"682L6IN"}]},"auxiliar":{}},{"grupo":"3","titular":{"docente":"Por Designar ...","horarios":[{"dia":"LU","hora":"18:45-20:15","aula":"682L8IN"},{"dia":"JU","hora":"12:45-14:15","aula":"642"},{"dia":"VI","hora":"18:45-20:15","aula":"682L6IN"}]},"auxiliar":{}}]},{"nombre":"TRABAJO DIRIGIDO (OPCIONAL)","sis":"2016040","nivel":"J","grupos":[{"grupo":"1","titular":{"docente":"ARNEZ CAMACHO MARIA DEL CARMEN","horarios":[{"dia":"LU","hora":"11:15-14:15","aula":"682L6IN"},{"dia":"MA","hora":"6:45-8:15","aula":"682L0IN"}]},"auxiliar":{}}]},{"nombre":"PSICOLOGIA INDUSTRIAL","sis":"2016041","nivel":"J","grupos":[{"grupo":"1","titular":{"docente":"JAUREGUI CARRASCO MARIA IVONNE","horarios":[{"dia":"MI","hora":"8:15-10:30","aula":"682L6IN"}]},"auxiliar":{}},{"grupo":"2","titular":{"docente":"JAUREGUI CARRASCO MARIA IVONNE","horarios":[{"dia":"VI","hora":"8:15-10:30","aula":"682L6IN"}]},"auxiliar":{}}]},{"nombre":"GESTION ESTRATEGICA DE EMPRESAS","sis":"2016059","nivel":"J","grupos":[{"grupo":"1","titular":{"docente":"GUZMAN ORELLANA GONZALO ENRIQUE","horarios":[{"dia":"LU","hora":"6:45-9:45","aula":"682L6IN"},{"dia":"MI","hora":"6:45-8:15","aula":"682L6IN"}]},"auxiliar":{}},{"grupo":"3","titular":{"docente":"GUZMAN ORELLANA GONZALO ENRIQUE","horarios":[{"dia":"MA","hora":"9:45-11:15","aula":"682L6IN"},{"dia":"JU","hora":"6:45-9:45","aula":"682L6IN"}]},"auxiliar":{}}]},{"nombre":"PRACTICA EMPRESARIAL","sis":"2016090","nivel":"J","grupos":[{"grupo":"1","titular":{"docente":"Por Designar ...","horarios":[{"dia":"MI","hora":"8:15-9:45","aula":"682L0IN"}]},"auxiliar":{}},{"grupo":"2","titular":{"docente":"Por Designar ...","horarios":[{"dia":"LU","hora":"18:45-20:15","aula":"682L7IN"}]},"auxiliar":{}},{"grupo":"3","titular":{"docente":"Por Designar ...","horarios":[{"dia":"VI","hora":"11:15-12:45","aula":"617"}]},"auxiliar":{}},{"grupo":"4","titular":{"docente":"Por Designar ...","horarios":[{"dia":"LU","hora":"9:45-11:15","aula":"682L8IN"}]},"auxiliar":{}}]}]}